knwl/__init__.py
knwl/config.py
knwl/di.py
knwl/framework_base.py
knwl/knwl.py
knwl/logging.py
knwl/services.py
knwl/utils.py
knwl/chunking/__init__.py
knwl/chunking/chunking_base.py
knwl/chunking/tiktoken_chunking.py
knwl/cli/cli.py
knwl/cli/cli_utils.py
knwl/cli/config_app.py
knwl/cli/graph_app.py
knwl/cli/info_app.py
knwl/extraction/__init__.py
knwl/extraction/basic_entity_extraction.py
knwl/extraction/basic_graph_extraction.py
knwl/extraction/basic_keywords_extraction.py
knwl/extraction/entity_extraction_base.py
knwl/extraction/glean_graph_extraction.py
knwl/extraction/graph_extraction_base.py
knwl/extraction/keywords_extraction_base.py
knwl/format/__init__.py
knwl/format/formatter_base.py
knwl/format/html_formatter.py
knwl/format/markdown_formatter.py
knwl/format/terminal/__init__.py
knwl/format/terminal/model_formatters.py
knwl/format/terminal/rich_formatter.py
knwl/format/terminal/service_formatters.py
knwl/format/terminal/terminal_formatter.py
knwl/llm/__init__.py
knwl/llm/anthropic.py
knwl/llm/json_llm_cache.py
knwl/llm/llm_base.py
knwl/llm/llm_cache_base.py
knwl/llm/ollama.py
knwl/llm/openai.py
knwl/models/KnwlAnswer.py
knwl/models/KnwlBlob.py
knwl/models/KnwlChunk.py
knwl/models/KnwlContext.py
knwl/models/KnwlDocument.py
knwl/models/KnwlEdge.py
knwl/models/KnwlEntity.py
knwl/models/KnwlExtraction.py
knwl/models/KnwlGraph.py
knwl/models/KnwlIngestion.py
knwl/models/KnwlInput.py
knwl/models/KnwlKeywords.py
knwl/models/KnwlModel.py
knwl/models/KnwlNode.py
knwl/models/KnwlParams.py
knwl/models/KnwlReference.py
knwl/models/KnwlResponse.py
knwl/models/KnwlText.py
knwl/models/__init__.py
knwl/prompts/__init__.py
knwl/prompts/extraction_prompts.py
knwl/prompts/prompt_constants.py
knwl/prompts/prompts.py
knwl/prompts/rag_prompts.py
knwl/prompts/summarization_prompts.py
knwl/prompts/templates/fast_entity_extraction.txt
knwl/prompts/templates/fast_graph_extraction.txt
knwl/prompts/templates/full_graph_extraction.txt
knwl/prompts/templates/glean_break.txt
knwl-1.8.0.dist-info/METADATA
knwl-1.8.0.dist-info/WHEEL
knwl-1.8.0.dist-info/entry_points.txt
knwl-1.8.0.dist-info/licenses/LICENSE
knwl-1.8.0.dist-info/RECORD
