Metadata-Version: 2.4
Name: knwl
Version: 1.8.0
Summary: A flexible Graph RAG package with advanced ingestion and augmentation strategies.
Project-URL: Homepage, https://github.com/Orbifold/knwl
Project-URL: Repository, https://github.com/Orbifold/knwl
Project-URL: Documentation, https://github.com/Orbifold/knwl
Author-email: "Francois Vanderseypen (Orbifold Consulting)" <swa@orbifold.net>
License-Expression: MIT
License-File: LICENSE
Requires-Python: <3.13,>=3.10
Requires-Dist: anthropic>=0.72.0
Requires-Dist: chromadb>=1.1.1
Requires-Dist: lxml>=6.0.2
Requires-Dist: networkx>=3.4.2
Requires-Dist: ollama>=0.4.7
Requires-Dist: openai>=1.53.0
Requires-Dist: pydantic>=2.0.0
Requires-Dist: rich>=13.0.0
Requires-Dist: tiktoken>=0.8.0
Requires-Dist: torch>=2.5.1
Requires-Dist: transformers>=4.46.1
Requires-Dist: typer>=0.20.0
